fslvbmparsers/__init__.py
fslvbmparsers/parsers.py
fslvbmparsers-0.0.2.dist-info/LICENSE.txt
fslvbmparsers-0.0.2.dist-info/METADATA
fslvbmparsers-0.0.2.dist-info/WHEEL
fslvbmparsers-0.0.2.dist-info/top_level.txt
fslvbmparsers-0.0.2.dist-info/RECORD
