Metadata-Version: 2.1
Name: fslvbmparsers
Version: 0.0.2
Summary: fsl and vbm parsers
Home-page: UNKNOWN
Author: Fatemeh
Author-email: 
License: UNKNOWN
Platform: UNKNOWN
Classifier: Programming Language :: Python :: 3
Classifier: License :: OSI Approved :: MIT License
Requires-Dist: pandas (>=0.20.3)
Requires-Dist: nibabel (>=3.1.1)
Requires-Dist: numpy (>=1.16.5)
